RealTimeProgrammingLectureNotesWaterlooCs452/README.md
RealTimeProgrammingLectureNotesWaterlooCs452/__init__.py
RealTimeProgrammingLectureNotesWaterlooCs452/__main__.py
RealTimeProgrammingLectureNotesWaterlooCs452/file.epub
RealTimeProgrammingLectureNotesWaterlooCs452/index.html
RealTimeProgrammingLectureNotesWaterlooCs452/css/__init__.py
RealTimeProgrammingLectureNotesWaterlooCs452/css/annotations.css
RealTimeProgrammingLectureNotesWaterlooCs452/css/main.css
RealTimeProgrammingLectureNotesWaterlooCs452/css/normalize.css
RealTimeProgrammingLectureNotesWaterlooCs452/css/popup.css
RealTimeProgrammingLectureNotesWaterlooCs452/font/__init__.py
RealTimeProgrammingLectureNotesWaterlooCs452/font/fontello.eot
RealTimeProgrammingLectureNotesWaterlooCs452/font/fontello.svg
RealTimeProgrammingLectureNotesWaterlooCs452/font/fontello.ttf
RealTimeProgrammingLectureNotesWaterlooCs452/font/fontello.woff
RealTimeProgrammingLectureNotesWaterlooCs452/img/__init__.py
RealTimeProgrammingLectureNotesWaterlooCs452/img/annotator-glyph-sprite.png
RealTimeProgrammingLectureNotesWaterlooCs452/img/annotator-icon-sprite.png
RealTimeProgrammingLectureNotesWaterlooCs452/img/apple-touch-icon.png
RealTimeProgrammingLectureNotesWaterlooCs452/img/cancelfullscreen.png
RealTimeProgrammingLectureNotesWaterlooCs452/img/close.png
RealTimeProgrammingLectureNotesWaterlooCs452/img/fullscreen.png
RealTimeProgrammingLectureNotesWaterlooCs452/img/loader.gif
RealTimeProgrammingLectureNotesWaterlooCs452/img/menu-icon.png
RealTimeProgrammingLectureNotesWaterlooCs452/img/save.png
RealTimeProgrammingLectureNotesWaterlooCs452/img/saved.png
RealTimeProgrammingLectureNotesWaterlooCs452/img/settings-s.png
RealTimeProgrammingLectureNotesWaterlooCs452/img/settings.png
RealTimeProgrammingLectureNotesWaterlooCs452/img/star.png
RealTimeProgrammingLectureNotesWaterlooCs452/js/__init__.py
RealTimeProgrammingLectureNotesWaterlooCs452/js/epub.js
RealTimeProgrammingLectureNotesWaterlooCs452/js/epub.min.js
real_time_programming_lecture_notes_waterloo_cs452-2024.3.2.0.dist-info/METADATA
real_time_programming_lecture_notes_waterloo_cs452-2024.3.2.0.dist-info/WHEEL
real_time_programming_lecture_notes_waterloo_cs452-2024.3.2.0.dist-info/entry_points.txt
real_time_programming_lecture_notes_waterloo_cs452-2024.3.2.0.dist-info/top_level.txt
real_time_programming_lecture_notes_waterloo_cs452-2024.3.2.0.dist-info/RECORD
